odoo/addons/account_promissory_note_santander/README.rst
odoo/addons/account_promissory_note_santander/__init__.py
odoo/addons/account_promissory_note_santander/__manifest__.py
odoo/addons/account_promissory_note_santander/data/account_promissory_note_report_data.xml
odoo/addons/account_promissory_note_santander/i18n/account_promissory_note_santander.pot
odoo/addons/account_promissory_note_santander/i18n/es.po
odoo/addons/account_promissory_note_santander/readme/CONFIGURE.rst
odoo/addons/account_promissory_note_santander/readme/CONTRIBUTORS.rst
odoo/addons/account_promissory_note_santander/readme/DESCRIPTION.rst
odoo/addons/account_promissory_note_santander/readme/USAGE.rst
odoo/addons/account_promissory_note_santander/report/__init__.py
odoo/addons/account_promissory_note_santander/report/account_promissory_note_writing_report.xml
odoo/addons/account_promissory_note_santander/report/check_print.py
odoo/addons/account_promissory_note_santander/static/description/icon.png
odoo/addons/account_promissory_note_santander/static/description/index.html
odoo/addons/account_promissory_note_santander/views/report_promissory_note.xml
odoo12_addon_account_promissory_note_santander-12.0.1.0.0.99.dev4.dist-info/METADATA
odoo12_addon_account_promissory_note_santander-12.0.1.0.0.99.dev4.dist-info/WHEEL
odoo12_addon_account_promissory_note_santander-12.0.1.0.0.99.dev4.dist-info/top_level.txt
odoo12_addon_account_promissory_note_santander-12.0.1.0.0.99.dev4.dist-info/RECORD
